LICENSE
MANIFEST.in
README.md
fastentrypoints.py
setup.cfg
setup.py
evo/LICENSE
evo/__init__.py
evo/aggregate_ape_results.py
evo/common_ape_rpe.py
evo/entry_points.py
evo/ipython_config.py
evo/main_ape.py
evo/main_config.py
evo/main_evaluation.py
evo/main_evo.py
evo/main_fig.py
evo/main_ipython.py
evo/main_res.py
evo/main_rpe.py
evo/main_traj.py
evo/regression_simple.py
evo/version
evo/core/__init__.py
evo/core/filters.py
evo/core/geometry.py
evo/core/lie_algebra.py
evo/core/metrics.py
evo/core/result.py
evo/core/sync.py
evo/core/trajectory.py
evo/core/transformations.py
evo/tools/__init__.py
evo/tools/compat.py
evo/tools/file_interface.py
evo/tools/log.py
evo/tools/pandas_bridge.py
evo/tools/plot.py
evo/tools/settings.py
evo/tools/settings_template.py
evo/tools/user.py
evo_1.egg-info/PKG-INFO
evo_1.egg-info/SOURCES.txt
evo_1.egg-info/dependency_links.txt
evo_1.egg-info/entry_points.txt
evo_1.egg-info/not-zip-safe
evo_1.egg-info/requires.txt
evo_1.egg-info/top_level.txt
test/test_file_interface.py
test/test_filters.py
test/test_lie_algebra.py
test/test_trajectory.py