Metadata-Version: 1.1
Name: evo-1
Version: 1.1.2
Summary: Python package for the evaluation of odometry and SLAM
Home-page: https://github.com/ToniRV/evo-1
Author: Antoni Rosinol, Michael Grupp
Author-email: arosinol@mit.edu,
License: GPLv3
Keywords: SLAM,odometry,trajectory,evaluation,metric,vision,laser,visual,robotics
Platform: UNKNOWN
Classifier: License :: OSI Approved :: GNU General Public License v3 (GPLv3)
Classifier: Topic :: Scientific/Engineering
Classifier: Programming Language :: Python
Classifier: Programming Language :: Python :: 2.7
Classifier: Programming Language :: Python :: 3
Classifier: Programming Language :: Python :: 3.3
Classifier: Programming Language :: Python :: 3.4
Classifier: Programming Language :: Python :: 3.5
Classifier: Programming Language :: Python :: 3.6
Classifier: Programming Language :: Python :: Implementation :: CPython
